README.txt
setup.py
docs/devel_config.ini
fluncrunner/__init__.py
fluncrunner/main.py
fluncrunner.egg-info/PKG-INFO
fluncrunner.egg-info/SOURCES.txt
fluncrunner.egg-info/dependency_links.txt
fluncrunner.egg-info/entry_points.txt
fluncrunner.egg-info/not-zip-safe
fluncrunner.egg-info/requires.txt
fluncrunner.egg-info/top_level.txt