Metadata-Version: 1.0
Name: fluncrunner
Version: 0.0
Summary: Run flunc tests through the web
Home-page: UNKNOWN
Author: UNKNOWN
Author-email: UNKNOWN
License: UNKNOWN
Platform: UNKNOWN
